<INVENTORY>
  <ITEM>
    <ITEMTYPE>P</ITEMTYPE>
    <ITEMID>32039</ITEMID>
    <MINQTY>1</MINQTY>
  </ITEM>
  <ITEM>
    <ITEMTYPE>P</ITEMTYPE>
    <ITEMID>32073</ITEMID>
    <MINQTY>3</MINQTY>
    <COLOR>9</COLOR>
  </ITEM>
  <ITEM>
    <ITEMTYPE>P</ITEMTYPE>
    <ITEMID>3666</ITEMID>
    <MINQTY>2</MINQTY>
    <COLOR>63</COLOR>
  </ITEM>
  <ITEM>
    <ITEMTYPE>P</ITEMTYPE>
    <ITEMID>3701</ITEMID>
    <MINQTY>2</MINQTY>
    <COLOR>39</COLOR>
  </ITEM>
  <ITEM>
    <ITEMTYPE>P</ITEMTYPE>
    <ITEMID>3702</ITEMID>
    <MINQTY>2</MINQTY>
    <COLOR>6</COLOR>
  </ITEM>
  <ITEM>
    <ITEMTYPE>P</ITEMTYPE>
    <ITEMID>3713</ITEMID>
    <MINQTY>2</MINQTY>
  </ITEM>
  <ITEM>
    <ITEMTYPE>P</ITEMTYPE>
    <ITEMID>4519</ITEMID>
    <MINQTY>1</MINQTY>
    <COLOR>88</COLOR>
  </ITEM>
  <ITEM>
    <ITEMTYPE>P</ITEMTYPE>
    <ITEMID>60483</ITEMID>
    <MINQTY>1</MINQTY>
    <COLOR>11</COLOR>
  </ITEM>
  <ITEM>
    <ITEMTYPE>P</ITEMTYPE>
    <ITEMID>65249</ITEMID>
    <MINQTY>1</MINQTY>
  </ITEM>
  <ITEM>
    <ITEMTYPE>P</ITEMTYPE>
    <ITEMID>6538c</ITEMID>
    <MINQTY>5</MINQTY>
    <COLOR>5</COLOR>
  </ITEM>
  <ITEM>
    <ITEMTYPE>P</ITEMTYPE>
    <ITEMID>6628</ITEMID>
    <MINQTY>1</MINQTY>
    <COLOR>9</COLOR>
  </ITEM>
</INVENTORY>
